<annotation>
	<folder>images</folder>
	<filename>495.jpg</filename>
	<path>C:\Users\achraf_k\Desktop\achraf\ANPR\images\495.jpg</path>
	<source>
		<database>Unknown</database>
	</source>
	<size>
		<width>1497</width>
		<height>2000</height>
		<depth>3</depth>
	</size>
	<segmented>0</segmented>
	<object>
		<name>LP</name>
		<pose>Unspecified</pose>
		<truncated>0</truncated>
		<difficult>0</difficult>
		<bndbox>
			<xmin>1083</xmin>
			<ymin>874</ymin>
			<xmax>1280</xmax>
			<ymax>939</ymax>
		</bndbox>
	</object>
</annotation>
